<?xml version='1.0'?>
<ns2:test-suite xmlns:ns2='urn:model.allure.qatools.yandex.ru' start='1605452172622' stop='1605452326175'>
    <name>Content Management Policy Editing @content-management-policy-editing</name>
    <title>Content Management Policy Editing @content-management-policy-editing</title>
    <test-cases>
        <test-case start='1605452172624' status='passed' stop='1605452198181'>
            <name>A user can cancel any updates that they have done to the policy by pressing cancel {"FileType":"word","ContentFlags":"embeddedFiles","CurrentFlagType":"disallow","ChangedFlagType":"sanitise"} @functional @smoke @TEST-188</name>
            <title>A user can cancel any updates that they have done to the policy by pressing cancel {"FileType":"word","ContentFlags":"embeddedFiles","CurrentFlagType":"disallow","ChangedFlagType":"sanitise"} @functional @smoke @TEST-188</title>
            <labels>
                <label name='tag' value='@content-management-policy-editing'/>
                <label name='tag' value='@functional'/>
                <label name='tag' value='@smoke'/>
                <label name='tag' value='@TEST-188'/>
            </labels>
            <parameters/>
            <steps>
                <step start='1605452193474' status='passed' stop='1605452195921'>
                    <name>policyPage: setFlagTypeForGivenContentFlagsForGivenDocType "embeddedFiles", "word", "sanitise"</name>
                    <title>policyPage: setFlagTypeForGivenContentFlagsForGivenDocType "embeddedFiles", "word", "sanitise"</title>
                    <attachments/>
                    <steps>
                        <step start='1605452193474' status='passed' stop='1605452195816'>
                            <name>I click "label[for='word-id-2sanitise']"</name>
                            <title>I click "label[for='word-id-2sanitise']"</title>
                            <attachments/>
                            <steps/>
                        </step>
                    </steps>
                </step>
                <step start='1605452195921' status='passed' stop='1605452198175'>
                    <name>policyPage: clickCancelChanges </name>
                    <title>policyPage: clickCancelChanges </title>
                    <attachments/>
                    <steps>
                        <step start='1605452195921' status='passed' stop='1605452198175'>
                            <name>I click "//button[text()='Cancel Changes']"</name>
                            <title>I click "//button[text()='Cancel Changes']"</title>
                            <attachments/>
                            <steps/>
                        </step>
                    </steps>
                </step>
                <step start='1605452198175' status='passed' stop='1605452198180'>
                    <name>policyPage: assertElementChecked "input[id='word-id-2disallow']"</name>
                    <title>policyPage: assertElementChecked "input[id='word-id-2disallow']"</title>
                    <attachments/>
                    <steps>
                        <step start='1605452198175' status='passed' stop='1605452198180'>
                            <name>I see attributes on elements "input[id='word-id-2disallow']", {"checked":true}</name>
                            <title>I see attributes on elements "input[id='word-id-2disallow']", {"checked":true}</title>
                            <attachments/>
                            <steps/>
                        </step>
                    </steps>
                </step>
            </steps>
            <attachments/>
        </test-case>
        <test-case start='1605452198353' status='passed' stop='1605452221999'>
            <name>I can edit policy content flags {"FileType":"word","ContentFlags":"embeddedFiles","FlagType":"sanitise"} @functional @smoke @TEST-155</name>
            <title>I can edit policy content flags {"FileType":"word","ContentFlags":"embeddedFiles","FlagType":"sanitise"} @functional @smoke @TEST-155</title>
            <labels>
                <label name='tag' value='@content-management-policy-editing'/>
                <label name='tag' value='@functional'/>
                <label name='tag' value='@smoke'/>
                <label name='tag' value='@TEST-155'/>
            </labels>
            <parameters/>
            <steps>
                <step start='1605452217306' status='passed' stop='1605452219764'>
                    <name>policyPage: setFlagTypeForGivenContentFlagsForGivenDocType "embeddedFiles", "word", "sanitise"</name>
                    <title>policyPage: setFlagTypeForGivenContentFlagsForGivenDocType "embeddedFiles", "word", "sanitise"</title>
                    <attachments/>
                    <steps>
                        <step start='1605452217306' status='passed' stop='1605452219660'>
                            <name>I click "label[for='word-id-2sanitise']"</name>
                            <title>I click "label[for='word-id-2sanitise']"</title>
                            <attachments/>
                            <steps/>
                        </step>
                    </steps>
                </step>
                <step start='1605452219764' status='passed' stop='1605452221992'>
                    <name>policyPage: clickSaveChanges </name>
                    <title>policyPage: clickSaveChanges </title>
                    <attachments/>
                    <steps>
                        <step start='1605452219764' status='passed' stop='1605452221992'>
                            <name>I click "//button[text()='Save Changes']"</name>
                            <title>I click "//button[text()='Save Changes']"</title>
                            <attachments/>
                            <steps/>
                        </step>
                    </steps>
                </step>
                <step start='1605452221992' status='passed' stop='1605452221999'>
                    <name>policyPage: assertElementChecked "input[id='word-id-2sanitise']"</name>
                    <title>policyPage: assertElementChecked "input[id='word-id-2sanitise']"</title>
                    <attachments/>
                    <steps>
                        <step start='1605452221992' status='passed' stop='1605452221999'>
                            <name>I see attributes on elements "input[id='word-id-2sanitise']", {"checked":true}</name>
                            <title>I see attributes on elements "input[id='word-id-2sanitise']", {"checked":true}</title>
                            <attachments/>
                            <steps/>
                        </step>
                    </steps>
                </step>
            </steps>
            <attachments/>
        </test-case>
        <test-case start='1605452222155' status='passed' stop='1605452245451'>
            <name>I can edit policy content flags {"FileType":"excel","ContentFlags":"externalHyperlinks","FlagType":"disallow"} @functional @smoke @TEST-155</name>
            <title>I can edit policy content flags {"FileType":"excel","ContentFlags":"externalHyperlinks","FlagType":"disallow"} @functional @smoke @TEST-155</title>
            <labels>
                <label name='tag' value='@content-management-policy-editing'/>
                <label name='tag' value='@functional'/>
                <label name='tag' value='@smoke'/>
                <label name='tag' value='@TEST-155'/>
            </labels>
            <parameters/>
            <steps>
                <step start='1605452240741' status='passed' stop='1605452243182'>
                    <name>policyPage: setFlagTypeForGivenContentFlagsForGivenDocType "externalHyperlinks", "excel", "disallow"</name>
                    <title>policyPage: setFlagTypeForGivenContentFlagsForGivenDocType "externalHyperlinks", "excel", "disallow"</title>
                    <attachments/>
                    <steps>
                        <step start='1605452240741' status='passed' stop='1605452243082'>
                            <name>I click "label[for='excel-id-4disallow']"</name>
                            <title>I click "label[for='excel-id-4disallow']"</title>
                            <attachments/>
                            <steps/>
                        </step>
                    </steps>
                </step>
                <step start='1605452243182' status='passed' stop='1605452245446'>
                    <name>policyPage: clickSaveChanges </name>
                    <title>policyPage: clickSaveChanges </title>
                    <attachments/>
                    <steps>
                        <step start='1605452243182' status='passed' stop='1605452245446'>
                            <name>I click "//button[text()='Save Changes']"</name>
                            <title>I click "//button[text()='Save Changes']"</title>
                            <attachments/>
                            <steps/>
                        </step>
                    </steps>
                </step>
                <step start='1605452245446' status='passed' stop='1605452245451'>
                    <name>policyPage: assertElementChecked "input[id='excel-id-4disallow']"</name>
                    <title>policyPage: assertElementChecked "input[id='excel-id-4disallow']"</title>
                    <attachments/>
                    <steps>
                        <step start='1605452245446' status='passed' stop='1605452245451'>
                            <name>I see attributes on elements "input[id='excel-id-4disallow']", {"checked":true}</name>
                            <title>I see attributes on elements "input[id='excel-id-4disallow']", {"checked":true}</title>
                            <attachments/>
                            <steps/>
                        </step>
                    </steps>
                </step>
            </steps>
            <attachments/>
        </test-case>
        <test-case start='1605452245624' status='passed' stop='1605452285335'>
            <name>A user is able to change all content flags for all file type in policy page {"FileType":"word","FlagType":"sanitise"} @functional @smoke @TEST-Change-all-content-flag-for-all-doc-type</name>
            <title>A user is able to change all content flags for all file type in policy page {"FileType":"word","FlagType":"sanitise"} @functional @smoke @TEST-Change-all-content-flag-for-all-doc-type</title>
            <labels>
                <label name='tag' value='@content-management-policy-editing'/>
                <label name='tag' value='@functional'/>
                <label name='tag' value='@smoke'/>
                <label name='tag' value='@TEST-Change-all-content-flag-for-all-doc-type'/>
            </labels>
            <parameters/>
            <steps>
                <step start='1605452263161' status='passed' stop='1605452283015'>
                    <name>policyPage: clickSanitiseForAllFlag "word"</name>
                    <title>policyPage: clickSanitiseForAllFlag "word"</title>
                    <attachments/>
                    <steps>
                        <step start='1605452263161' status='passed' stop='1605452265566'>
                            <name>I click "label[for='word-id-1sanitise']"</name>
                            <title>I click "label[for='word-id-1sanitise']"</title>
                            <attachments/>
                            <steps/>
                        </step>
                        <step start='1605452265666' status='passed' stop='1605452268036'>
                            <name>I click "label[for='word-id-2sanitise']"</name>
                            <title>I click "label[for='word-id-2sanitise']"</title>
                            <attachments/>
                            <steps/>
                        </step>
                        <step start='1605452268136' status='passed' stop='1605452270467'>
                            <name>I click "label[for='word-id-3sanitise']"</name>
                            <title>I click "label[for='word-id-3sanitise']"</title>
                            <attachments/>
                            <steps/>
                        </step>
                        <step start='1605452270568' status='passed' stop='1605452272937'>
                            <name>I click "label[for='word-id-4sanitise']"</name>
                            <title>I click "label[for='word-id-4sanitise']"</title>
                            <attachments/>
                            <steps/>
                        </step>
                        <step start='1605452273041' status='passed' stop='1605452275419'>
                            <name>I click "label[for='word-id-5sanitise']"</name>
                            <title>I click "label[for='word-id-5sanitise']"</title>
                            <attachments/>
                            <steps/>
                        </step>
                        <step start='1605452275520' status='passed' stop='1605452277902'>
                            <name>I click "label[for='word-id-6sanitise']"</name>
                            <title>I click "label[for='word-id-6sanitise']"</title>
                            <attachments/>
                            <steps/>
                        </step>
                        <step start='1605452278007' status='passed' stop='1605452280470'>
                            <name>I click "label[for='word-id-7sanitise']"</name>
                            <title>I click "label[for='word-id-7sanitise']"</title>
                            <attachments/>
                            <steps/>
                        </step>
                        <step start='1605452280572' status='passed' stop='1605452282915'>
                            <name>I click "label[for='word-id-8sanitise']"</name>
                            <title>I click "label[for='word-id-8sanitise']"</title>
                            <attachments/>
                            <steps/>
                        </step>
                    </steps>
                </step>
                <step start='1605452283015' status='passed' stop='1605452285263'>
                    <name>policyPage: clickSaveChanges </name>
                    <title>policyPage: clickSaveChanges </title>
                    <attachments/>
                    <steps>
                        <step start='1605452283015' status='passed' stop='1605452285262'>
                            <name>I click "//button[text()='Save Changes']"</name>
                            <title>I click "//button[text()='Save Changes']"</title>
                            <attachments/>
                            <steps/>
                        </step>
                    </steps>
                </step>
                <step start='1605452285263' status='passed' stop='1605452285335'>
                    <name>policyPage: assertElementChecked "input[id='word-id-8sanitise']"</name>
                    <title>policyPage: assertElementChecked "input[id='word-id-8sanitise']"</title>
                    <attachments/>
                    <steps>
                        <step start='1605452285263' status='passed' stop='1605452285276'>
                            <name>I see attributes on elements "input[id='word-id-1sanitise']", {"checked":true}</name>
                            <title>I see attributes on elements "input[id='word-id-1sanitise']", {"checked":true}</title>
                            <attachments/>
                            <steps/>
                        </step>
                        <step start='1605452285277' status='passed' stop='1605452285289'>
                            <name>I see attributes on elements "input[id='word-id-2sanitise']", {"checked":true}</name>
                            <title>I see attributes on elements "input[id='word-id-2sanitise']", {"checked":true}</title>
                            <attachments/>
                            <steps/>
                        </step>
                        <step start='1605452285290' status='passed' stop='1605452285300'>
                            <name>I see attributes on elements "input[id='word-id-3sanitise']", {"checked":true}</name>
                            <title>I see attributes on elements "input[id='word-id-3sanitise']", {"checked":true}</title>
                            <attachments/>
                            <steps/>
                        </step>
                        <step start='1605452285301' status='passed' stop='1605452285308'>
                            <name>I see attributes on elements "input[id='word-id-4sanitise']", {"checked":true}</name>
                            <title>I see attributes on elements "input[id='word-id-4sanitise']", {"checked":true}</title>
                            <attachments/>
                            <steps/>
                        </step>
                        <step start='1605452285309' status='passed' stop='1605452285314'>
                            <name>I see attributes on elements "input[id='word-id-5sanitise']", {"checked":true}</name>
                            <title>I see attributes on elements "input[id='word-id-5sanitise']", {"checked":true}</title>
                            <attachments/>
                            <steps/>
                        </step>
                        <step start='1605452285314' status='passed' stop='1605452285322'>
                            <name>I see attributes on elements "input[id='word-id-6sanitise']", {"checked":true}</name>
                            <title>I see attributes on elements "input[id='word-id-6sanitise']", {"checked":true}</title>
                            <attachments/>
                            <steps/>
                        </step>
                        <step start='1605452285322' status='passed' stop='1605452285330'>
                            <name>I see attributes on elements "input[id='word-id-7sanitise']", {"checked":true}</name>
                            <title>I see attributes on elements "input[id='word-id-7sanitise']", {"checked":true}</title>
                            <attachments/>
                            <steps/>
                        </step>
                        <step start='1605452285330' status='passed' stop='1605452285335'>
                            <name>I see attributes on elements "input[id='word-id-8sanitise']", {"checked":true}</name>
                            <title>I see attributes on elements "input[id='word-id-8sanitise']", {"checked":true}</title>
                            <attachments/>
                            <steps/>
                        </step>
                    </steps>
                </step>
            </steps>
            <attachments/>
        </test-case>
        <test-case start='1605452285474' status='passed' stop='1605452326026'>
            <name>A user is able to change all content flags for all file type in policy page {"FileType":"pdf","FlagType":"disallow"} @functional @smoke @TEST-Change-all-content-flag-for-all-doc-type</name>
            <title>A user is able to change all content flags for all file type in policy page {"FileType":"pdf","FlagType":"disallow"} @functional @smoke @TEST-Change-all-content-flag-for-all-doc-type</title>
            <labels>
                <label name='tag' value='@content-management-policy-editing'/>
                <label name='tag' value='@functional'/>
                <label name='tag' value='@smoke'/>
                <label name='tag' value='@TEST-Change-all-content-flag-for-all-doc-type'/>
            </labels>
            <parameters/>
            <steps>
                <step start='1605452304075' status='passed' stop='1605452323734'>
                    <name>policyPage: clickDisallowForAllFlag "pdf"</name>
                    <title>policyPage: clickDisallowForAllFlag "pdf"</title>
                    <attachments/>
                    <steps>
                        <step start='1605452304075' status='passed' stop='1605452306439'>
                            <name>I click "label[for='pdf-id-1disallow']"</name>
                            <title>I click "label[for='pdf-id-1disallow']"</title>
                            <attachments/>
                            <steps/>
                        </step>
                        <step start='1605452306539' status='passed' stop='1605452308891'>
                            <name>I click "label[for='pdf-id-2disallow']"</name>
                            <title>I click "label[for='pdf-id-2disallow']"</title>
                            <attachments/>
                            <steps/>
                        </step>
                        <step start='1605452308992' status='passed' stop='1605452311331'>
                            <name>I click "label[for='pdf-id-3disallow']"</name>
                            <title>I click "label[for='pdf-id-3disallow']"</title>
                            <attachments/>
                            <steps/>
                        </step>
                        <step start='1605452311447' status='passed' stop='1605452313787'>
                            <name>I click "label[for='pdf-id-4disallow']"</name>
                            <title>I click "label[for='pdf-id-4disallow']"</title>
                            <attachments/>
                            <steps/>
                        </step>
                        <step start='1605452313888' status='passed' stop='1605452316240'>
                            <name>I click "label[for='pdf-id-5disallow']"</name>
                            <title>I click "label[for='pdf-id-5disallow']"</title>
                            <attachments/>
                            <steps/>
                        </step>
                        <step start='1605452316341' status='passed' stop='1605452318721'>
                            <name>I click "label[for='pdf-id-6disallow']"</name>
                            <title>I click "label[for='pdf-id-6disallow']"</title>
                            <attachments/>
                            <steps/>
                        </step>
                        <step start='1605452318823' status='passed' stop='1605452321153'>
                            <name>I click "label[for='pdf-id-7disallow']"</name>
                            <title>I click "label[for='pdf-id-7disallow']"</title>
                            <attachments/>
                            <steps/>
                        </step>
                        <step start='1605452321255' status='passed' stop='1605452323633'>
                            <name>I click "label[for='pdf-id-8disallow']"</name>
                            <title>I click "label[for='pdf-id-8disallow']"</title>
                            <attachments/>
                            <steps/>
                        </step>
                    </steps>
                </step>
                <step start='1605452323734' status='passed' stop='1605452325982'>
                    <name>policyPage: clickSaveChanges </name>
                    <title>policyPage: clickSaveChanges </title>
                    <attachments/>
                    <steps>
                        <step start='1605452323734' status='passed' stop='1605452325981'>
                            <name>I click "//button[text()='Save Changes']"</name>
                            <title>I click "//button[text()='Save Changes']"</title>
                            <attachments/>
                            <steps/>
                        </step>
                    </steps>
                </step>
                <step start='1605452325982' status='passed' stop='1605452326026'>
                    <name>policyPage: assertElementChecked "input[id='pdf-id-8disallow']"</name>
                    <title>policyPage: assertElementChecked "input[id='pdf-id-8disallow']"</title>
                    <attachments/>
                    <steps>
                        <step start='1605452325982' status='passed' stop='1605452325990'>
                            <name>I see attributes on elements "input[id='pdf-id-1disallow']", {"checked":true}</name>
                            <title>I see attributes on elements "input[id='pdf-id-1disallow']", {"checked":true}</title>
                            <attachments/>
                            <steps/>
                        </step>
                        <step start='1605452325990' status='passed' stop='1605452325997'>
                            <name>I see attributes on elements "input[id='pdf-id-2disallow']", {"checked":true}</name>
                            <title>I see attributes on elements "input[id='pdf-id-2disallow']", {"checked":true}</title>
                            <attachments/>
                            <steps/>
                        </step>
                        <step start='1605452325997' status='passed' stop='1605452326002'>
                            <name>I see attributes on elements "input[id='pdf-id-3disallow']", {"checked":true}</name>
                            <title>I see attributes on elements "input[id='pdf-id-3disallow']", {"checked":true}</title>
                            <attachments/>
                            <steps/>
                        </step>
                        <step start='1605452326002' status='passed' stop='1605452326006'>
                            <name>I see attributes on elements "input[id='pdf-id-4disallow']", {"checked":true}</name>
                            <title>I see attributes on elements "input[id='pdf-id-4disallow']", {"checked":true}</title>
                            <attachments/>
                            <steps/>
                        </step>
                        <step start='1605452326006' status='passed' stop='1605452326014'>
                            <name>I see attributes on elements "input[id='pdf-id-5disallow']", {"checked":true}</name>
                            <title>I see attributes on elements "input[id='pdf-id-5disallow']", {"checked":true}</title>
                            <attachments/>
                            <steps/>
                        </step>
                        <step start='1605452326014' status='passed' stop='1605452326018'>
                            <name>I see attributes on elements "input[id='pdf-id-6disallow']", {"checked":true}</name>
                            <title>I see attributes on elements "input[id='pdf-id-6disallow']", {"checked":true}</title>
                            <attachments/>
                            <steps/>
                        </step>
                        <step start='1605452326019' status='passed' stop='1605452326022'>
                            <name>I see attributes on elements "input[id='pdf-id-7disallow']", {"checked":true}</name>
                            <title>I see attributes on elements "input[id='pdf-id-7disallow']", {"checked":true}</title>
                            <attachments/>
                            <steps/>
                        </step>
                        <step start='1605452326022' status='passed' stop='1605452326026'>
                            <name>I see attributes on elements "input[id='pdf-id-8disallow']", {"checked":true}</name>
                            <title>I see attributes on elements "input[id='pdf-id-8disallow']", {"checked":true}</title>
                            <attachments/>
                            <steps/>
                        </step>
                    </steps>
                </step>
            </steps>
            <attachments/>
        </test-case>
    </test-cases>
</ns2:test-suite>